schemawizard_package/.schemawiz_config1
schemawizard_package/.schemawiz_config2
schemawizard_package/.schemawiz_config3
schemawizard_package/__init__.py
schemawizard_package/a.csv
schemawizard_package/floats.csv
schemawizard_package/postgres_data.tsv
schemawizard_package/sample7.csv
schemawizard_package/schemawizard.py
schemawizard_package/servers.csv
schemawizard_package/sqlite.station_years.ddl
schemawizard_package/sqlite.tablea.ddl
schemawizard_package/sqlite.tablec.ddl
schemawizard_package/station_months.tsv
schemawizard_package/station_years.tsv
schemawizard_package/test.csv
schemawizard_package/testcase1.csv
schemawizard_package/testconnects.py
schemawizard_package/z.canweather.station_years.ddl
schemawizard_package-2.5.2.dist-info/METADATA
schemawizard_package-2.5.2.dist-info/WHEEL
schemawizard_package-2.5.2.dist-info/licenses/LICENSE
schemawizard_package-2.5.2.dist-info/RECORD
